{
    "fluentMethods": true,
    "relationships": [],
    "fields": [
        {
            "fieldName": "entityType",
            "fieldType": "String"
        },
        {
            "fieldName": "entityId",
            "fieldType": "Long"
        },
        {
            "fieldName": "path",
            "fieldType": "String"
        },
        {
            "fieldName": "fileName",
            "fieldType": "String"
        },
		{
            "fieldName": "sequence",
            "fieldType": "Integer"
        },
        {
            "fieldName": "description",
            "fieldType": "String"
        },
        {
            "fieldName": "createdBy",
            "fieldType": "String"
        },
        {
            "fieldName": "createdDate",
            "fieldType": "ZonedDateTime"
        },
        {
            "fieldName": "lastModifiedBy",
            "fieldType": "String"
        },
        {
            "fieldName": "lastModifiedDate",
            "fieldType": "ZonedDateTime"
        }
    ],
    "changelogDate": "20180221114443",
    "entityTableName": "url",
    "dto": "mapstruct",
    "pagination": "pagination",
    "service": "serviceClass",
    "jpaMetamodelFiltering": false
}
